objectlib/__init__.py
objectlib/combinatorics/__init__.py
objectlib/combinatorics/counting.py
objectlib/evolution/__init__.py
objectlib/evolution/candidate.py
objectlib/evolution/crossover.py
objectlib/evolution/evolutionary.py
objectlib/evolution/genetic.py
objectlib/evolution/mutation.py
objectlib/evolution/selection.py
objectlib/probability/__init__.py
objectlib/probability/distributions.py
objectlib/probability/sampling.py
objectlib/utils/__init__.py
objectlib/utils/dataloader.py
objectlib/utils/generator.py
objectlib/utils/naming.py
objectlib/utils/options.py
objectlib/utils/selection.py
objectlib/utils/timing.py
objectlib-0.0.1.dist-info/LICENSE
objectlib-0.0.1.dist-info/METADATA
objectlib-0.0.1.dist-info/WHEEL
objectlib-0.0.1.dist-info/top_level.txt
objectlib-0.0.1.dist-info/RECORD
